django_listview_filters/__init__.py
django_listview_filters/_helpers.py
django_listview_filters/_settings.py
django_listview_filters/filters.py
django_listview_filters/mixins.py
django_listview_filters-0.0.1b1.dev3.dist-info/METADATA
django_listview_filters-0.0.1b1.dev3.dist-info/WHEEL
django_listview_filters-0.0.1b1.dev3.dist-info/licenses/LICENSE
django_listview_filters-0.0.1b1.dev3.dist-info/RECORD
