Metadata-Version: 2.1
Name: django_listview_filters
Version: 0.0.1b1.dev3
Summary: Add context to list views for sidebar links and modifying querysets with those links.
Project-URL: Homepage, https://git.tricity.wsu.edu/karl.wooster/django-listview-filters
Project-URL: Bug Tracker, https://git.tricity.wsu.edu/karl.wooster/django-listview-filters/-/issues
Project-URL: Documentation, https://django-listview-filters.readthedocs.io/en/latest/
Author-email: Karl Wooster <karl.wooster@wsu.edu>
License: MIT License
License-File: LICENSE
Classifier: License :: OSI Approved :: MIT License
Classifier: Operating System :: OS Independent
Classifier: Programming Language :: Python :: 3
Requires-Python: >=3.10
Requires-Dist: django
Requires-Dist: furl
